{"9a9cb10iINWhe2HjHCoBZg==":"s41395095.jpg","WEzNuRqRuQ7wk55Q17Gqtg==":"s76502928.jpg","9vy5ILlcg9Sofz5IHWxxIA==":"mbr.jpg","jz89WzPUwtJPqfVY7uMx1A==":"s70346234.jpg","rXH1botycB9bnTxFaD4rZQ==":"14189935.jpg","6qQSgxpA/6v/sss1OzQM6w==":"42700456.jpg","cfLvt5hX0L+oCDdVUxlpBQ==":"91634812.jpg","oRykAiO0rUD++7AmPeEwUg==":"background1.jpg","r+JFjVHC1NfP242xh6xErQ==":"mbr-1920x984.png","5QkFHz5S+SRtZzlhDEdAYQ==":"s02425835-400x146.jpg","94eknV9PmOlDmVq7O1VO1w==":"s47671390-600x504.jpg","gAi+Q+t5whVuabcniJJRXw==":"mbr-1920x1280.jpg","Aa8sEVDLHGBLiWzWVSKdlg==":"%D0%B8%D0%B7%D0%BE%D0%B1%D1%80%D0%B0%D0%B6%D0%B5%D0%BD%D0%B8%D0%B5_viber_2021-05-04_12-17-27-605-96x57.png","lK4R7BCXY5Z8prwjG2oDZA==":"%D0%B8%D0%B7%D0%BE%D0%B1%D1%80%D0%B0%D0%B6%D0%B5%D0%BD%D0%B8%D0%B5_viber_2021-05-04_12-17-27-605-96x57.png","80PQyeipkjUbz1wtMClkfA==":"-.png","HYpUayH3WRjSQ8klOSnu+A==":"-viber-2021-05-04-12-17-27-605-128x76_1.png"}